Randmathcli/__init__.py
Randmathcli/__main__.py
randmathcli-1.0.0.dist-info/licenses/LICENSE
randmathcli-1.0.0.dist-info/METADATA
randmathcli-1.0.0.dist-info/WHEEL
randmathcli-1.0.0.dist-info/entry_points.txt
randmathcli-1.0.0.dist-info/top_level.txt
randmathcli-1.0.0.dist-info/RECORD
