Metadata-Version: 2.4
Name: Randmathcli
Version: 1.0.0
Summary: A Random Math Problem Generator
Author: Mahdi Ruiz
License-Expression: MIT
Project-URL: Homepage, https://github.com/Mrdev88/Randmathcli
Project-URL: Issues, https://github.com/Mrdev88/Randmathcli/issues
License-File: LICENSE
Requires-Dist: click>=8.1.3
Dynamic: license-file
